S1-hola-mundo/hola_mundo.v
module hola (
    input wire a, // Signal de entrada de tipo wire (Se utilia para vables)
    output wire y // Es una salida de tipo wire, es un cable que transporta la señal de salida
);

    // Asignación continua: lo que pase en 'a' se refleja en 'y'
    assign y = a;

endmodule

S1-hola-mundo/tb_hola_mundo.v
// Un testbench simula el comportamiento del modulo hola_mundo.v

// Funciona para generar entradas (estimulos) y observar las salidas

// Este testbench:
// 1) Instancia el modulo hola (DTU = Device Under Test)
// 2) Genera señales de entrada para el modulo hola (cada 10 ns)
// 3) Genera el archivo dump.vcd

//  `timescale define la unidad de tiempo y la precision
//  `timescale 1ns / 1ps significa que la unidad de tiempo es 1 nanosegundo

`timescale 1ns / 1ps

module tb_hola_mundo;

    // Señales para conectar al DUT
    reg a; // Señal de entrada de tipo reg (Se utiliza para variables en testbenches)
    wire y; // Señal de salida de tipo wire

    // Instancia del DUT (Device Under Test)
    hola dut (
        .a(a),
        .y(y)
    );

    // Generación de señales de entrada
    initial begin
        // Inicialización
        a = 0;

        // Cambiar la señal 'a' cada 10 ns
        forever begin
            #10 a = ~a; // Invertir el valor de 'a' cada 10 ns
        end
    end

    // Generación del archivo VCD para simulación
    initial begin
        $dumpfile("tb_hola_mundo.vcd"); // Nombre del archivo VCD
        $dumpvars(0, tb_hola_mundo);    // Volcar todas las variables del testbench
        #100;                            // Simular por 100 ns
        $finish;                         // Finalizar la simulación
    end

endmodule

S1-hola-mundo/tb_hola_mundo.vcd
$date
	Tue Jan 20 20:45:19 2026
$end
$version
	Icarus Verilog
$end
$timescale
	1ps
$end
$scope module tb_hola_mundo $end
$var wire 1 ! y $end
$var reg 1 " a $end
$scope module dut $end
$var wire 1 " a $end
$var wire 1 ! y $end
$upscope $end
$upscope $end
$enddefinitions $end
$comment Show the parameter values. $end
$dumpall
$end
#0
$dumpvars
0"
0!
$end
#10000
1!
1"
#20000
0!
0"
#30000
1!
1"
#40000
0!
0"
#50000
1!
1"
#60000
0!
0"
#70000
1!
1"
#80000
0!
0"
#90000
1!
1"
#100000
0!
0"
